pywarper/__init__.py
pywarper/stats.py
pywarper/surface.py
pywarper/utils.py
pywarper/warpers.py
pywarper-0.2.4.dist-info/METADATA
pywarper-0.2.4.dist-info/WHEEL
pywarper-0.2.4.dist-info/licenses/LICENSE
pywarper-0.2.4.dist-info/RECORD
