Metadata-Version: 2.4
Name: pywarper
Version: 0.2.4
Summary: Conformal mapping-based warping of retinal morphologies.
License-Expression: GPL-3.0-or-later
License-File: LICENSE
Requires-Python: >=3.10.0
Requires-Dist: alphashape>=1.3.1
Requires-Dist: numpy>=2.2.0
Requires-Dist: pygridfit>=0.1.5
Requires-Dist: scipy>=1.15.0
Requires-Dist: skeliner>=0.2.3
Requires-Dist: watermark>=2.5.0
Provides-Extra: dev
Requires-Dist: ipykernel; extra == 'dev'
Requires-Dist: maturin; extra == 'dev'
Requires-Dist: pytest; extra == 'dev'
Requires-Dist: ruff; extra == 'dev'
Requires-Dist: twine; extra == 'dev'
Provides-Extra: scikit-sparse
Requires-Dist: pygridfit[scikit-sparse]>=0.1.4; extra == 'scikit-sparse'
Requires-Dist: scikit-sparse>=0.4.15; extra == 'scikit-sparse'
